ismobile/__init__.py
ismobile/middleware.py
ismobile/utils.py
django_ismobile-1.0.2.dist-info/LICENSE
django_ismobile-1.0.2.dist-info/WHEEL
django_ismobile-1.0.2.dist-info/METADATA
django_ismobile-1.0.2.dist-info/RECORD
